vmm_manager/__init__.py
vmm_manager/__main__.py
vmm_manager/entity/action.py
vmm_manager/entity/inventory.py
vmm_manager/entity/plan.py
vmm_manager/entity/vm.py
vmm_manager/entity/vm_ansible.py
vmm_manager/entity/vm_disk.py
vmm_manager/entity/vm_network.py
vmm_manager/includes/ps_templates/add_operation_lock.j2
vmm_manager/includes/ps_templates/clean_objects_after_vm_creation.j2
vmm_manager/includes/ps_templates/connection_test.j2
vmm_manager/includes/ps_templates/convert_vm_disk.j2
vmm_manager/includes/ps_templates/create_vm.j2
vmm_manager/includes/ps_templates/create_vm_disk.j2
vmm_manager/includes/ps_templates/create_vm_pos.j2
vmm_manager/includes/ps_templates/delete_vm.j2
vmm_manager/includes/ps_templates/delete_vm_disk.j2
vmm_manager/includes/ps_templates/expand_vm_disk.j2
vmm_manager/includes/ps_templates/get_additional_disks.j2
vmm_manager/includes/ps_templates/get_available_regions.j2
vmm_manager/includes/ps_templates/get_vms_in_group.j2
vmm_manager/includes/ps_templates/list_options.j2
vmm_manager/includes/ps_templates/monitore_jobs.j2
vmm_manager/includes/ps_templates/move_vm_disk.j2
vmm_manager/includes/ps_templates/move_vm_region.j2
vmm_manager/includes/ps_templates/remove_operation_lock.j2
vmm_manager/includes/ps_templates/update_dynamic_memory.j2
vmm_manager/includes/ps_templates/update_nested_virtualization.j2
vmm_manager/includes/ps_templates/update_vm.j2
vmm_manager/includes/ps_templates/validate_inventory.j2
vmm_manager/includes/ps_templates/vmm_setup.j2
vmm_manager/includes/schema.yaml
vmm_manager/infra/__init__.py
vmm_manager/infra/access_server.py
vmm_manager/infra/command.py
vmm_manager/parser/__init__.py
vmm_manager/parser/parser_local.py
vmm_manager/parser/parser_remote.py
vmm_manager/scvmm/__init__.py
vmm_manager/scvmm/enums.py
vmm_manager/scvmm/scjob.py
vmm_manager/scvmm/scregion.py
vmm_manager/util/__init__.py
vmm_manager/util/config.py
vmm_manager/util/msgs.py
vmm_manager/util/operation.py
vmm_manager/vmm_manager.py
vmm_manager-1.3.0.dist-info/METADATA
vmm_manager-1.3.0.dist-info/WHEEL
vmm_manager-1.3.0.dist-info/entry_points.txt
vmm_manager-1.3.0.dist-info/licenses/LICENSE
vmm_manager-1.3.0.dist-info/RECORD
