Metadata-Version: 2.4
Name: vmm_manager
Version: 1.3.0
Summary: Management of resources on System Center Virtual Machine Manager (SCVMM) in a declarative way.
License: MIT
License-File: LICENSE
Keywords: IaC,scvmm,vmm_manager
Author: Estevão Costa
Author-email: ecosta@mpes.mp.br
Requires-Python: >=3.10,<4.0
Classifier: Development Status :: 5 - Production/Stable
Classifier: Intended Audience :: System Administrators
Classifier: License :: OSI Approved :: MIT License
Classifier: Operating System :: POSIX :: Linux
Classifier: Programming Language :: Python :: 3
Classifier: Programming Language :: Python :: 3.10
Classifier: Programming Language :: Python :: 3.11
Classifier: Programming Language :: Python :: 3.12
Classifier: Programming Language :: Python :: 3.13
Classifier: Programming Language :: Python :: 3.14
Classifier: Topic :: System :: Installation/Setup
Classifier: Topic :: System :: Systems Administration
Requires-Dist: configargparse (>=1,<2)
Requires-Dist: jinja2 (>=3,<4)
Requires-Dist: paramiko (>=4,<5)
Requires-Dist: pytz (>=2025.2)
Requires-Dist: ruamel.yaml (>=0.19,<0.20)
Requires-Dist: tqdm (>=4,<5)
Requires-Dist: yamale (>=6,<7)
Requires-Dist: yamlable (>=1,<2)
Project-URL: Documentation, https://github.com/MP-ES/vmm_manager
Project-URL: Homepage, https://github.com/MP-ES/vmm_manager
Project-URL: Repository, https://github.com/MP-ES/vmm_manager
